<?xml version="1.0"?>
<?xml-stylesheet type="text/xsl" href="configuration.xsl"?>

<configuration>
    <property>
        <name>hbase.rootdir</name>
        <value>hdfs://centos01:8020/hbase</value>
    </property>

    <property>
        <name>hbase.cluster.distributed</name>
        <value>true</value>
    </property>

    <property>
        <name>hbase.zookeeper.quorum</name>
        <value>centos01,centos02,centos03</value>
    </property>

    <property>
        <name>hbase.zookeeper.property.clientPort</name>
        <value>2181</value>
    </property>

    <!-- Zookeeper元数据快照的存储目录）  -->
    <property>
        <name>hbase.zookeeper.property.dataDir</name>
        <value>/opt/modules/hbase-2.2.4/zkData</value>
    </property>

    <!-- 指定HBase Master web页面访问端口，默认端口号16010 -->
    <property>
        <name>hbase.master.info.port</name>
        <value>16010</value>
    </property>

    <property>
        <name>hbase.regionserver.port</name>
        <value>16020</value>
    </property>

    <!-- 指定HBase RegionServer web页面访问端口，默认端口号16030 -->
    <property>
        <name>hbase.regionserver.info.port</name>
        <value>16030</value>
    </property>

    <property>
        <name>hbase.unsafe.stream.capability.enforce</name>
        <value>false</value>
    </property>

</configuration>
